straattaal_bijbel/__init__.py
straattaal_bijbel/dictionary.py
straattaal_bijbel/verse.py
straattaal_bijbel-97867967678689734589734258973489579438579384579384.0.dist-info/LICENSE
straattaal_bijbel-97867967678689734589734258973489579438579384579384.0.dist-info/METADATA
straattaal_bijbel-97867967678689734589734258973489579438579384579384.0.dist-info/WHEEL
straattaal_bijbel-97867967678689734589734258973489579438579384579384.0.dist-info/top_level.txt
straattaal_bijbel-97867967678689734589734258973489579438579384579384.0.dist-info/RECORD
