Metadata-Version: 2.1
Name: straattaal-bijbel
Version: 97867967678689734589734258973489579438579384579384.0
Summary: TYPE YOUR DESCRIPTION HERE
Home-page: https://github.com/Prutsor/bijbel-straattaal
Author: God
Author-email: god@prutsor.nl
License: Apache 2.0
Download-URL: https://github.com/Prutsor/bijbel-straattaal/archive/refs/tags/bijbel4life.tar.gz
Keywords: bijbel,god,patta
Platform: UNKNOWN
Classifier: Development Status :: 3 - Alpha
Classifier: Intended Audience :: Developers
Classifier: Topic :: Software Development :: Build Tools
Classifier: License :: OSI Approved :: MIT License
Classifier: Programming Language :: Python :: 3
Classifier: Programming Language :: Python :: 3.4
Classifier: Programming Language :: Python :: 3.5
Classifier: Programming Language :: Python :: 3.6
Classifier: Programming Language :: Python :: 3.9
License-File: LICENSE
Requires-Dist: validators
Requires-Dist: requests
